dbm_index/__init__.py
dbm_index/helpers.py
dbm_index/indexer.py
dbm_index/schemas.py
dbm_index/types.py
dbm_index-1.0.1.dist-info/METADATA
dbm_index-1.0.1.dist-info/WHEEL
dbm_index-1.0.1.dist-info/top_level.txt
dbm_index-1.0.1.dist-info/RECORD
